nv/__init__.py
nv/__version__.py
nv/cli.py
nv/core.py
nv/crypto.py
nv-0.0.7.dist-info/LICENSE
nv-0.0.7.dist-info/METADATA
nv-0.0.7.dist-info/WHEEL
nv-0.0.7.dist-info/entry_points.txt
nv-0.0.7.dist-info/top_level.txt
nv-0.0.7.dist-info/RECORD
