Metadata-Version: 2.1
Name: nv
Version: 0.0.7
Summary: A utility for managing multiple configurations & environments
License: Copyright 2017 Nathan Muir        
Project-URL: Homepage, https://github.com/3stack-software/nv
Classifier: Intended Audience :: Developers
Classifier: Intended Audience :: System Administrators
Classifier: License :: OSI Approved :: Apache Software License
Classifier: Programming Language :: Python :: 3
Classifier: Programming Language :: Python :: 3.6
Classifier: Programming Language :: Python :: 3.7
Requires-Python: >=3.7
License-File: LICENSE
Requires-Dist: sh
Requires-Dist: boto3
Requires-Dist: click
Requires-Dist: cryptography
Requires-Dist: keyring
